setup.py
aminetoolkit/EDA.py
aminetoolkit/__init__.py
aminetoolkit.egg-info/PKG-INFO
aminetoolkit.egg-info/SOURCES.txt
aminetoolkit.egg-info/dependency_links.txt
aminetoolkit.egg-info/not-zip-safe
aminetoolkit.egg-info/top_level.txt