Metadata-Version: 1.0
Name: aminetoolkit
Version: 0.1
Summary: Tools I like to use
Home-page: UNKNOWN
Author: Amine Bouamama
Author-email: amine.bouamama@gmail.com
License: MIT
Platform: UNKNOWN
